brailleify/__init__.py
brailleify/solution.py
brailleify-0.4.dist-info/LICENSE.md
brailleify-0.4.dist-info/METADATA
brailleify-0.4.dist-info/WHEEL
brailleify-0.4.dist-info/top_level.txt
brailleify-0.4.dist-info/RECORD
